{"meta":{"candidate_name":"Kelly, Mackenzie","candidate_slug":"kelly","office":"Austin City Council","generated_at":"2026-04-07T16:49:26.000487+00:00"},"hero":{"total_raised":239546,"unique_donors":1287,"total_contributions":1600,"employer_affiliated_pct":56.1,"top_industry":"Real Estate"},"by_year":[{"year":"2023","count":148,"total":41690},{"year":"2024","count":1452,"total":197857}],"interest_groups":[{"label":"Not Employed","donors":509,"total":68823,"color":"#6b7280","noDonut":true},{"label":"Real Estate","donors":127,"total":37856,"color":"#f59e0b"},{"label":"Unknown","donors":144,"total":27590,"color":"#1f2937"},{"label":"Technology","donors":96,"total":15363,"color":"#4f8ef7"},{"label":"Government","donors":60,"total":10385,"color":"#818cf8"},{"label":"Retail / Media / Other","donors":50,"total":10168,"color":"#374151"},{"label":"Finance","donors":42,"total":9865,"color":"#fbbf24"},{"label":"Consulting / PR","donors":35,"total":9815,"color":"#94a3b8"},{"label":"Education","donors":49,"total":8625,"color":"#22d3ee"},{"label":"Legal","donors":38,"total":8505,"color":"#a78bfa"},{"label":"Healthcare","donors":41,"total":8357,"color":"#f472b6"},{"label":"Self-Employed","donors":38,"total":8225,"color":"#78716c","noDonut":true},{"label":"Construction","donors":19,"total":5365,"color":"#d97706"},{"label":"Energy / Environment","donors":9,"total":3075,"color":"#ef4444"},{"label":"Engineering","donors":13,"total":2635,"color":"#6b7280"},{"label":"Nonprofit / Advocacy","donors":14,"total":2500,"color":"#34d399"},{"label":"Hospitality / Events","donors":6,"total":1900,"color":"#fb923c"},{"label":"Student","donors":3,"total":495,"color":"#38bdf8","noDonut":true}],"notable_firms":[{"firm":"Endeavor Real Estate","industry":"Real Estate","tags":"real-estate-development","donors":32,"total":11350,"color":"#f59e0b"},{"firm":"Armbrust  & Brown","industry":"Real Estate","tags":"real-estate-development","donors":27,"total":10875,"color":"#f59e0b"},{"firm":"Attorney","industry":"Legal","tags":"","donors":15,"total":3425,"color":"#a78bfa"},{"firm":"City of Austin","industry":"Government","tags":"self-employed","donors":11,"total":2275,"color":"#818cf8"},{"firm":"University of Texas at Austin","industry":"Education","tags":"not-employed","donors":10,"total":2220,"color":"#22d3ee"},{"firm":"Real Estate Investor","industry":"Real Estate","tags":"not-employed","donors":3,"total":1800,"color":"#f59e0b"},{"firm":"STATE OF TEXAS","industry":"Government","tags":"not-employed","donors":9,"total":1635,"color":"#818cf8"},{"firm":"HPI","industry":"Real Estate","tags":"real-estate-development","donors":4,"total":1375,"color":"#f59e0b"},{"firm":"Physician","industry":"Healthcare","tags":"self-employed","donors":4,"total":1150,"color":"#f472b6"},{"firm":"IBM","industry":"Technology","tags":"not-employed","donors":7,"total":1133,"color":"#4f8ef7"},{"firm":"Realtor","industry":"Real Estate","tags":"self-employed","donors":8,"total":1075,"color":"#f59e0b"},{"firm":"Director","industry":"Media","tags":"","donors":4,"total":1050,"color":"#60a5fa"},{"firm":"Austin ISD","industry":"Education","tags":"not-employed","donors":3,"total":950,"color":"#22d3ee"},{"firm":"Amazon","industry":"Technology","tags":"tech-startup-ecosystem","donors":4,"total":800,"color":"#4f8ef7"},{"firm":"Consulting","industry":"Consulting / PR","tags":"not-employed","donors":9,"total":725,"color":"#94a3b8"},{"firm":"Texas A&M University","industry":"Education","tags":"not-employed","donors":4,"total":700,"color":"#22d3ee"},{"firm":"Oracle","industry":"Technology","tags":"tech-startup-ecosystem","donors":4,"total":700,"color":"#4f8ef7"},{"firm":"Austin Police Department","industry":"Government","tags":"not-employed","donors":6,"total":700,"color":"#818cf8"},{"firm":"Doctor","industry":"Healthcare","tags":"","donors":3,"total":675,"color":"#f472b6"},{"firm":"DELL","industry":"Technology","tags":"not-employed","donors":7,"total":675,"color":"#4f8ef7"}],"top_donors":[{"name":"Ogden, Susan","employer":"Real Estate Investor","industry":"Real Estate","tags":"not-employed","total":900,"count":2},{"name":"Jenkins, Robert","employer":"ABC Home & Commercial","industry":"Consulting / PR","tags":"","total":900,"count":2},{"name":"Lundgren, Wallace","employer":"Not Employed","industry":"Not Employed","tags":"not-employed","total":900,"count":2},{"name":"Hampsten, Phil","employer":"Hampsten Consulting","industry":"Consulting / PR","tags":"","total":900,"count":2},{"name":"Lindsey, Mack","employer":"Not Employed","industry":"Not Employed","tags":"not-employed","total":900,"count":2},{"name":"Agny, Rajesh","employer":"Not Employed","industry":"Not Employed","tags":"not-employed","total":701,"count":2},{"name":"Johnson, Corry","employer":"Not Employed","industry":"Not Employed","tags":"not-employed","total":650,"count":3},{"name":"Sellers, Craig","employer":"Not Employed","industry":"Not Employed","tags":"not-employed","total":600,"count":6},{"name":"Ingels, Kirk","employer":"Ingels Insurance Agency","industry":"Finance","tags":"","total":550,"count":2},{"name":"Emerson, Jennifer","employer":"Hennessy Advisors","industry":"Finance","tags":"","total":550,"count":2}],"cycles":[{"label":"Initial Run","election_year":2024,"year_range":"2023–2025","hero":{"total_raised":386314,"unique_donors":1909,"total_contributions":2548,"employer_affiliated_pct":58.3,"top_industry":"Real Estate"},"interest_groups":[{"label":"Not Employed","donors":704,"total":104337,"color":"#6b7280","noDonut":true},{"label":"Real Estate","donors":171,"total":51128,"color":"#f59e0b"},{"label":"Government","donors":107,"total":45189,"color":"#818cf8"},{"label":"Unknown","donors":242,"total":43059,"color":"#1f2937"},{"label":"Technology","donors":144,"total":23142,"color":"#4f8ef7"},{"label":"Retail / Media / Other","donors":76,"total":15684,"color":"#374151"},{"label":"Finance","donors":65,"total":14777,"color":"#fbbf24"},{"label":"Healthcare","donors":64,"total":13530,"color":"#f472b6"},{"label":"Self-Employed","donors":74,"total":13241,"color":"#78716c","noDonut":true},{"label":"Legal","donors":59,"total":13209,"color":"#a78bfa"},{"label":"Education","donors":70,"total":12604,"color":"#22d3ee"},{"label":"Consulting / PR","donors":45,"total":11093,"color":"#94a3b8"},{"label":"Construction","donors":41,"total":10722,"color":"#d97706"},{"label":"Energy / Environment","donors":12,"total":4385,"color":"#ef4444"},{"label":"Engineering","donors":20,"total":3878,"color":"#6b7280"},{"label":"Nonprofit / Advocacy","donors":15,"total":3118,"color":"#34d399"},{"label":"Hospitality / Events","donors":9,"total":2725,"color":"#fb923c"},{"label":"Student","donors":3,"total":495,"color":"#38bdf8","noDonut":true}],"notable_firms":[{"firm":"City of Austin","industry":"Government","tags":"","donors":29,"total":31256,"color":"#818cf8"},{"firm":"Endeavor Real Estate","industry":"Real Estate","tags":"real-estate-development","donors":33,"total":11550,"color":"#f59e0b"},{"firm":"Armbrust  & Brown","industry":"Real Estate","tags":"real-estate-development","donors":27,"total":10875,"color":"#f59e0b"},{"firm":"Attorney","industry":"Legal","tags":"not-employed","donors":26,"total":5969,"color":"#a78bfa"},{"firm":"Real Estate Investor","industry":"Real Estate","tags":"self-employed","donors":4,"total":3100,"color":"#f59e0b"},{"firm":"STATE OF TEXAS","industry":"Government","tags":"","donors":14,"total":2994,"color":"#818cf8"},{"firm":"Continental Automotive Group","industry":"Retail","tags":"not-employed","donors":6,"total":2900,"color":"#a3e635"},{"firm":"University of Texas at Austin","industry":"Education","tags":"higher-education","donors":11,"total":2290,"color":"#22d3ee"},{"firm":"Realtor","industry":"Real Estate","tags":"self-employed","donors":11,"total":2175,"color":"#f59e0b"},{"firm":"Physician","industry":"Healthcare","tags":"","donors":10,"total":2150,"color":"#f472b6"},{"firm":"Software Engineer","industry":"Technology","tags":"","donors":10,"total":1909,"color":"#4f8ef7"},{"firm":"IBM","industry":"Technology","tags":"tech-startup-ecosystem","donors":11,"total":1907,"color":"#4f8ef7"},{"firm":"Teacher","industry":"Education","tags":"","donors":8,"total":1875,"color":"#22d3ee"},{"firm":"HPI","industry":"Real Estate","tags":"real-estate-development","donors":5,"total":1775,"color":"#f59e0b"},{"firm":"Heritage Title Company","industry":"Real Estate","tags":"real-estate-development","donors":4,"total":1650,"color":"#f59e0b"},{"firm":"Senox Corporation","industry":"Construction","tags":"","donors":5,"total":1550,"color":"#d97706"},{"firm":"Principal","industry":"Education","tags":"not-employed","donors":6,"total":1550,"color":"#22d3ee"},{"firm":"CPA","industry":"Finance","tags":"self-employed","donors":5,"total":1500,"color":"#fbbf24"},{"firm":"Real Estate","industry":"Real Estate","tags":"","donors":4,"total":1300,"color":"#f59e0b"},{"firm":"DELL","industry":"Technology","tags":"tech-startup-ecosystem","donors":12,"total":1285,"color":"#4f8ef7"}],"top_donors":[{"name":"Lindsey, Mack","employer":"Not Employed","industry":"Not Employed","tags":"not-employed","total":1500,"count":4},{"name":"Ogden, Susan","employer":"Real Estate Investor","industry":"Real Estate","tags":"self-employed","total":1300,"count":3},{"name":"Smith, Ken","employer":"KSI Hospitality","industry":"Unknown","tags":"","total":1282,"count":5},{"name":"Hock, Stacy","employer":"Not Employed","industry":"Not Employed","tags":"not-employed","total":1250,"count":3},{"name":"mayfield, robert","employer":"Mayfield Dairy Queen","industry":"Unknown","tags":"","total":1250,"count":3},{"name":"Jackson, Kacee","employer":"Real Estate Investor","industry":"Real Estate","tags":"","total":1250,"count":3},{"name":"Langford, Brenda","employer":"Not Employed","industry":"Not Employed","tags":"not-employed","total":1250,"count":3},{"name":"Sellers, Tom","employer":"ConocoPhillips","industry":"Energy / Environment","tags":"fossil-fuel-advocacy|energy-mineral-rights","total":1100,"count":3},{"name":"Knight, Dan","employer":"Not Employed","industry":"Not Employed","tags":"not-employed","total":1100,"count":4},{"name":"Blythe, Sharon","employer":"CPA","industry":"Finance","tags":"not-employed","total":1000,"count":4}]},{"label":"Reelection","election_year":2028,"year_range":"2026–present","hero":{"total_raised":0,"unique_donors":0,"total_contributions":0,"employer_affiliated_pct":0.0,"top_industry":"Unknown"},"interest_groups":[],"notable_firms":[],"top_donors":[]}]}