[
 {
  "donor_id": "tcv-d56b2169-9faa-4a11-afe0-81841aec388f",
  "name": "Dwight, Diane",
  "zip": "78735",
  "county_total": 250,
  "gave_to": "Shea, Brigid",
  "occupations": "",
  "employer_strings": "",
  "locations": "Austin, TX 78735",
  "first_gift": "2022-02-14",
  "last_gift": "2022-02-14",
  "fec_partisan_lean": 1.0,
  "fec_donation_count": 142
 },
 {
  "donor_id": "tcv-d4458ffe-0ea7-4517-b107-e27cc8a1faeb",
  "name": "Hayes, Emmitt",
  "zip": "",
  "county_total": 250,
  "gave_to": "Travillion, Jeff",
  "occupations": "",
  "employer_strings": "",
  "locations": "",
  "first_gift": "2021-11-09",
  "last_gift": "2021-11-09",
  "fec_partisan_lean": 1.0,
  "fec_donation_count": 10
 },
 {
  "donor_id": "tcv-cd044ebc-23e3-4999-8d08-195cad53afb0",
  "name": "Lloyd Doggett for Congress",
  "zip": "78702",
  "county_total": 250,
  "gave_to": "Morales, George",
  "occupations": "Congressman",
  "employer_strings": "U.S. Congress",
  "locations": "Austin, TX 78702",
  "first_gift": "2024-03-21",
  "last_gift": "2024-03-21",
  "fec_partisan_lean": 1.0,
  "fec_donation_count": 116
 },
 {
  "donor_id": "tcv-cc564705-bed8-4576-a485-84d928438e34",
  "name": "Morgan, Cameron",
  "zip": "78653",
  "county_total": 250,
  "gave_to": "Travillion, Jeff",
  "occupations": "",
  "employer_strings": "",
  "locations": "Manor, TX 78653-2233",
  "first_gift": "2025-08-26",
  "last_gift": "2025-08-26",
  "fec_partisan_lean": 0.0,
  "fec_donation_count": 2
 },
 {
  "donor_id": "tcv-c93af298-c462-4160-9190-03a31ec1d60d",
  "name": "Hershey, Jessica",
  "zip": "78703",
  "county_total": 250,
  "gave_to": "Brown, Andy",
  "occupations": "Hairstylist",
  "employer_strings": "Self",
  "locations": "Austin, TX 78703",
  "first_gift": "2022-10-21",
  "last_gift": "2022-10-21",
  "fec_partisan_lean": null,
  "fec_donation_count": 0
 },
 {
  "donor_id": "tcv-c35fec31-2d84-4d2c-9947-4fd993e4cbb5",
  "name": "Prisant, Martin",
  "zip": "78746",
  "county_total": 250,
  "gave_to": "Shea, Brigid",
  "occupations": "",
  "employer_strings": "",
  "locations": "Austin, TX 78746",
  "first_gift": "2017-10-23",
  "last_gift": "2022-02-28",
  "fec_partisan_lean": null,
  "fec_donation_count": 0
 },
 {
  "donor_id": "tcv-bcca2ce3-b383-4768-a64e-f2920eb3d6c1",
  "name": "Gosselink, Margaret",
  "zip": "",
  "county_total": 250,
  "gave_to": "Howard, Ann",
  "occupations": "",
  "employer_strings": "",
  "locations": "",
  "first_gift": "2021-10-25",
  "last_gift": "2021-10-25",
  "fec_partisan_lean": 1.0,
  "fec_donation_count": 293
 },
 {
  "donor_id": "tcv-b6218a15-5aaa-40d9-85cc-c83a3b857bb1",
  "name": "Price, Ann-Marie",
  "zip": "78704",
  "county_total": 250,
  "gave_to": "Howard, Ann",
  "occupations": "",
  "employer_strings": "",
  "locations": "Austin, TX 78704",
  "first_gift": "2023-10-04",
  "last_gift": "2023-10-04",
  "fec_partisan_lean": 1.0,
  "fec_donation_count": 11
 },
 {
  "donor_id": "tcv-af7c9fbf-4858-46f8-b29c-47836b670777",
  "name": "Campbell, Wilda",
  "zip": "78703",
  "county_total": 250,
  "gave_to": "Shea, Brigid",
  "occupations": "",
  "employer_strings": "",
  "locations": "Austin, TX 78703",
  "first_gift": "2021-12-31",
  "last_gift": "2021-12-31",
  "fec_partisan_lean": 0.9973393641080218,
  "fec_donation_count": 20
 },
 {
  "donor_id": "tcv-a92567eb-8bc5-4c37-ba17-771de6868ae8",
  "name": "Lehman, Chris",
  "zip": "78765",
  "county_total": 250,
  "gave_to": "Shea, Brigid",
  "occupations": "",
  "employer_strings": "",
  "locations": "Austin, TX 78765",
  "first_gift": "2022-06-09",
  "last_gift": "2022-06-09",
  "fec_partisan_lean": 0.9720788471020915,
  "fec_donation_count": 226
 },
 {
  "donor_id": "tcv-9bbe4893-031f-498a-bd6b-1e48b8014ff7",
  "name": "Schechter, Lillie",
  "zip": "77006",
  "county_total": 250,
  "gave_to": "Brown, Andy",
  "occupations": "Consultant",
  "employer_strings": "Self",
  "locations": "Houston, TX 77006",
  "first_gift": "2025-09-10",
  "last_gift": "2025-09-10",
  "fec_partisan_lean": 1.0,
  "fec_donation_count": 57
 },
 {
  "donor_id": "tcv-8dd2c542-6e75-4357-967a-c9ec42663528",
  "name": "Blair, Robert",
  "zip": "78746",
  "county_total": 250,
  "gave_to": "Shea, Brigid",
  "occupations": "",
  "employer_strings": "",
  "locations": "Austin, TX 78746-6117",
  "first_gift": "2025-06-26",
  "last_gift": "2025-06-26",
  "fec_partisan_lean": 0.14951648451147942,
  "fec_donation_count": 192
 }
]