[
 {
  "donor_id": "tcv-71b61765-84b5-46ac-978b-ff5f346d7694",
  "name": "Andy Brown Campaign",
  "zip": "78703",
  "county_total": 6030,
  "gave_to": "Travillion, Jeff,Shea, Brigid",
  "occupations": "",
  "employer_strings": "",
  "locations": "Austin, TX 78703-0002",
  "first_gift": "2025-08-13",
  "last_gift": "2026-01-01",
  "fec_partisan_lean": 1.0,
  "fec_donation_count": 1
 },
 {
  "donor_id": "tcv-51270ae7-0728-437c-a0ed-695daaee6e0a",
  "name": "Howe, Michael",
  "zip": "78728",
  "county_total": 6029,
  "gave_to": "Travillion, Jeff,Shea, Brigid,Howard, Ann",
  "occupations": "",
  "employer_strings": "",
  "locations": "Austin, TX 78728,Austin, TX 78728-4461",
  "first_gift": "2021-12-06",
  "last_gift": "2025-12-09",
  "fec_partisan_lean": 1.0,
  "fec_donation_count": 1
 },
 {
  "donor_id": "tcv-b385585f-ebf6-44b8-9985-350481e0e73a",
  "name": "Scott, John",
  "zip": "78702",
  "county_total": 6000,
  "gave_to": "Shea, Brigid,Howard, Ann",
  "occupations": "",
  "employer_strings": "",
  "locations": "Austin, TX 78702-5136",
  "first_gift": "2024-09-30",
  "last_gift": "2024-11-27",
  "fec_partisan_lean": null,
  "fec_donation_count": 0
 },
 {
  "donor_id": "51040b5a-ddf4-4c05-8ba8-2a8a16d521a1",
  "name": "Clark, Jennifer",
  "zip": "78704",
  "county_total": 5700,
  "gave_to": "Shea, Brigid",
  "occupations": "",
  "employer_strings": "",
  "locations": "Austin, TX 78704,Austin, TX 78704-5217",
  "first_gift": "2017-10-17",
  "last_gift": "2025-06-23",
  "fec_partisan_lean": 1.0,
  "fec_donation_count": 104
 },
 {
  "donor_id": "tcv-90ea8037-2695-404a-9e5e-30133815a4f4",
  "name": "Brockenbrough, Anne",
  "zip": "78653",
  "county_total": 5650,
  "gave_to": "Travillion, Jeff,Shea, Brigid,Howard, Ann",
  "occupations": "",
  "employer_strings": "",
  "locations": "Manor, TX 78653,Manor, TX 78653-5278",
  "first_gift": "2017-04-27",
  "last_gift": "2025-11-12",
  "fec_partisan_lean": 1.0,
  "fec_donation_count": 7
 },
 {
  "donor_id": "e274f5f1-53f7-4c0c-b088-a20904f254d0",
  "name": "Reese, Pamela",
  "zip": "78746",
  "county_total": 5500,
  "gave_to": "Shea, Brigid,Howard, Ann",
  "occupations": "",
  "employer_strings": "",
  "locations": "Austin, TX 78746",
  "first_gift": "2017-10-22",
  "last_gift": "2023-10-17",
  "fec_partisan_lean": 1.0,
  "fec_donation_count": 234
 },
 {
  "donor_id": "tcv-9a0e2cc2-e723-478c-b0b7-ed41674bc533",
  "name": "Wallace, Katharine",
  "zip": "78731",
  "county_total": 5358,
  "gave_to": "Brown, Andy",
  "occupations": "Office Manager,office manager",
  "employer_strings": "Lake Flato,Lake Flato Architects,Lake flato",
  "locations": "Austin, TX 78731,austin, TX 78731",
  "first_gift": "2021-12-24",
  "last_gift": "2025-12-24",
  "fec_partisan_lean": 1.0,
  "fec_donation_count": 12
 },
 {
  "donor_id": "cd26ffef-fcc4-4404-b90d-31f12514811d",
  "name": "Salinas, Derlis",
  "zip": "78701",
  "county_total": 5150,
  "gave_to": "Shea, Brigid,Howard, Ann",
  "occupations": "",
  "employer_strings": "",
  "locations": "Austin, TX 78701",
  "first_gift": "2022-12-07",
  "last_gift": "2025-06-08",
  "fec_partisan_lean": 1.0,
  "fec_donation_count": 20
 },
 {
  "donor_id": "tcv-59620d05-d74f-48b2-8864-5acf96e2cce0",
  "name": "Aubrey Mayo",
  "zip": "78704",
  "county_total": 5060,
  "gave_to": "Gomez, Margaret",
  "occupations": "NOT EMPLOYED",
  "employer_strings": "NOT EMPLOYED",
  "locations": "Austin, TX 78704",
  "first_gift": "2022-01-05",
  "last_gift": "2022-01-05",
  "fec_partisan_lean": 1.0,
  "fec_donation_count": 3
 },
 {
  "donor_id": "tcv-fdfca74e-48cf-434d-b269-d31ebb19ce0f",
  "name": "Walker, Sara",
  "zip": "78212",
  "county_total": 5000,
  "gave_to": "Brown, Andy",
  "occupations": "Event Planner",
  "employer_strings": "Self",
  "locations": "San Antonio, TX 78212",
  "first_gift": "2023-06-22",
  "last_gift": "2023-06-22",
  "fec_partisan_lean": 0.3096197020001539,
  "fec_donation_count": 153
 }
]